memkeep/__init__.py
memkeep/mem.py
memkeep-0.1.8.dist-info/WHEEL
memkeep-0.1.8.dist-info/METADATA
memkeep-0.1.8.dist-info/license_files/LICENSE
memkeep-0.1.8.dist-info/RECORD
